asyncua/__init__.py
asyncua/sync.py
asyncua/tools.py
asyncua/client/__init__.py
asyncua/client/client.py
asyncua/client/ua_client.py
asyncua/client/ua_file.py
asyncua/client/ua_file_transfer.py
asyncua/client/ha/__init__.py
asyncua/client/ha/common.py
asyncua/client/ha/ha_client.py
asyncua/client/ha/reconciliator.py
asyncua/client/ha/virtual_subscription.py
asyncua/common/__init__.py
asyncua/common/callback.py
asyncua/common/connection.py
asyncua/common/copy_node_util.py
asyncua/common/event_objects.py
asyncua/common/events.py
asyncua/common/instantiate_util.py
asyncua/common/manage_nodes.py
asyncua/common/methods.py
asyncua/common/node.py
asyncua/common/node_factory.py
asyncua/common/session_interface.py
asyncua/common/shortcuts.py
asyncua/common/sql_injection.py
asyncua/common/statemachine.py
asyncua/common/structures.py
asyncua/common/structures104.py
asyncua/common/subscription.py
asyncua/common/type_dictionary_builder.py
asyncua/common/ua_utils.py
asyncua/common/utils.py
asyncua/common/xmlexporter.py
asyncua/common/xmlimporter.py
asyncua/common/xmlparser.py
asyncua/crypto/__init__.py
asyncua/crypto/cert_gen.py
asyncua/crypto/permission_rules.py
asyncua/crypto/security_policies.py
asyncua/crypto/truststore.py
asyncua/crypto/uacrypto.py
asyncua/crypto/validator.py
asyncua/server/__init__.py
asyncua/server/address_space.py
asyncua/server/binary_server_asyncio.py
asyncua/server/event_generator.py
asyncua/server/history.py
asyncua/server/history_sql.py
asyncua/server/internal_server.py
asyncua/server/internal_session.py
asyncua/server/internal_subscription.py
asyncua/server/monitored_item_service.py
asyncua/server/server.py
asyncua/server/subscription_service.py
asyncua/server/uaprocessor.py
asyncua/server/user_managers.py
asyncua/server/users.py
asyncua/server/standard_address_space/__init__.py
asyncua/server/standard_address_space/standard_address_space.py
asyncua/server/standard_address_space/standard_address_space_services.py
asyncua/ua/__init__.py
asyncua-1.1.5.dist-info/COPYING
asyncua-1.1.5.dist-info/METADATA
asyncua-1.1.5.dist-info/WHEEL
asyncua-1.1.5.dist-info/entry_points.txt
asyncua-1.1.5.dist-info/top_level.txt
asyncua-1.1.5.dist-info/RECORD
