Metadata-Version: 2.1
Name: asyncua
Version: 1.1.5
Summary: Pure Python OPC-UA client and server library
Home-page: http://freeopcua.github.io/
Author: Olivier Roulet-Dubonnet
Author-email: olivier.roulet@gmail.com
License: GNU Lesser General Public License v3 or later
Classifier: Programming Language :: Python :: 3.7
Classifier: Programming Language :: Python :: 3.8
Classifier: Programming Language :: Python :: 3.9
Classifier: Programming Language :: Python :: 3.10
Classifier: Programming Language :: Python :: 3.11
Classifier: Development Status :: 4 - Beta
Classifier: Intended Audience :: Developers
Classifier: Operating System :: OS Independent
Classifier: License :: OSI Approved :: GNU Lesser General Public License v3 or later (LGPLv3+)
Classifier: Topic :: Software Development :: Libraries :: Python Modules
Provides: asyncua
License-File: COPYING
Requires-Dist: aiofiles
Requires-Dist: aiosqlite
Requires-Dist: python-dateutil
Requires-Dist: pytz
Requires-Dist: cryptography>42.0.0
Requires-Dist: sortedcontainers
Requires-Dist: importlib-metadata; python_version < "3.8"
Requires-Dist: pyOpenSSL>23.2.0
Requires-Dist: typing-extensions
